nte/__init__.py
nte/main.py
nte-0.0.6.dist-info/entry_points.txt
nte-0.0.6.dist-info/LICENSE
nte-0.0.6.dist-info/WHEEL
nte-0.0.6.dist-info/METADATA
nte-0.0.6.dist-info/RECORD
