Metadata-Version: 2.1
Name: nte
Version: 0.0.6
Summary: A CLI scratch pad for notes, commands, lists, etc
License: MIT
Author: Timothy Crosley
Author-email: timothy.crosley@gmail.com
Requires-Python: >=3.6,<4.0
Classifier: License :: OSI Approved :: MIT License
Classifier: Programming Language :: Python :: 3
Classifier: Programming Language :: Python :: 3.6
Classifier: Programming Language :: Python :: 3.7
Classifier: Programming Language :: Python :: 3.8
Classifier: Programming Language :: Python :: 3.9
Requires-Dist: colorama (>=0.4.4,<0.5.0)
Requires-Dist: rich (>=10.1.0,<11.0.0)
Requires-Dist: typer (>=0.3.2,<0.4.0)
